paque/__init__.py
paque/executor.py
paque/paque.py
paque/parser.py
paque/planner.py
paque/task.py
paque-0.1.1.dist-info/entry_points.txt
paque-0.1.1.dist-info/WHEEL
paque-0.1.1.dist-info/METADATA
paque-0.1.1.dist-info/RECORD
