Metadata-Version: 2.1
Name: paque
Version: 0.1.1
Summary: paque simplifies running simple workflows you want to run. It offers a few features of `make`, but removing most of its power
Home-page: https://github.com/rberenguel/paque
License: MIT
Author: Ruben Berenguel
Author-email: ruben+poetry@mostlymaths.net
Requires-Python: >=3.6,<4.0
Classifier: License :: OSI Approved :: MIT License
Classifier: Programming Language :: Python :: 3
Classifier: Programming Language :: Python :: 3.6
Classifier: Programming Language :: Python :: 3.7
Classifier: Programming Language :: Python :: 3.8
Requires-Dist: cleo (>=0.8.0,<0.9.0)
Requires-Dist: click (>=7.1.2,<8.0.0)
Requires-Dist: colorlog (>=4.1.0,<5.0.0)
Requires-Dist: pyyaml (>=5.3,<6.0)
Project-URL: Repository, https://github.com/rberenguel/paque
